pymochow/__init__.py
pymochow/compat.py
pymochow/configuration.py
pymochow/exception.py
pymochow/protocol.py
pymochow/utils.py
pymochow/ai/__init__.py
pymochow/ai/dochub/__init__.py
pymochow/ai/dochub/bos_dochub.py
pymochow/ai/dochub/dochub.py
pymochow/ai/dochub/local_dochub.py
pymochow/ai/embedder/__init__.py
pymochow/ai/embedder/embedder.py
pymochow/ai/embedder/qianfan_embedder.py
pymochow/ai/parser/__init__.py
pymochow/ai/parser/langchain_parser.py
pymochow/ai/parser/parser.py
pymochow/ai/pipeline/__init__.py
pymochow/ai/pipeline/default_pipeline.py
pymochow/ai/pipeline/pipeline.py
pymochow/ai/processor/__init__.py
pymochow/ai/processor/doc_processor.py
pymochow/ai/processor/langchain_doc_processor.py
pymochow/ai/processor/qianfan_doc_processor.py
pymochow/ai/splitter/__init__.py
pymochow/ai/splitter/langchain_splitter.py
pymochow/ai/splitter/splitter.py
pymochow/auth/__init__.py
pymochow/auth/bce_credentials.py
pymochow/auth/bce_v1_signer.py
pymochow/client/__init__.py
pymochow/client/mochow_client.py
pymochow/http/__init__.py
pymochow/http/handler.py
pymochow/http/http_client.py
pymochow/http/http_content_types.py
pymochow/http/http_headers.py
pymochow/http/http_methods.py
pymochow/http/http_response.py
pymochow/model/__init__.py
pymochow/model/database.py
pymochow/model/document.py
pymochow/model/enum.py
pymochow/model/schema.py
pymochow/model/table.py
pymochow/retry/__init__.py
pymochow/retry/retry_policy.py
pymochow-2.3.6.dist-info/LICENSE
pymochow-2.3.6.dist-info/METADATA
pymochow-2.3.6.dist-info/WHEEL
pymochow-2.3.6.dist-info/top_level.txt
pymochow-2.3.6.dist-info/RECORD
